{
  "title": "Math Alphabets",
  "displayLength": 4,
  "symbols": [
    {
      "name": "text",
      "text": "\\text{text - ABab12}",
      "value": "\\text{}",
      "caretPosition": 6
    },
    {
      "name": "mathbb",
      "text": "\\mathbb{mathbb - ABab12}",
      "value": "\\mathbb{}",
      "caretPosition": 8
    },
    {
      "name": "mathcal",
      "text": "\\mathcal{mathcal - ABab12}",
      "value": "\\mathcal{}",
      "caretPosition": 9
    },
    {
      "name": "mathrm",
      "text": "\\mathrm{mathrm - ABab12}",
      "value": "\\mathrm{}",
      "caretPosition": 8
    },
    {
      "name": "mathbf",
      "text": "\\mathbf{mathbf - ABab12}",
      "value": "\\mathbf{}",
      "caretPosition": 8
    },
    {
      "name": "mathit",
      "text": "\\mathit{mathit - ABab12}",
      "value": "\\mathit{}",
      "caretPosition": 8
    },
    {
      "name": "mathnormal",
      "text": "\\mathnormal{mathnormal - ABab12}",
      "value": "\\mathnormal{}",
      "caretPosition": 12
    },
    {
      "name": "mathsf",
      "text": "\\mathsf{mathsf - ABab12}",
      "value": "\\mathsf{}",
      "caretPosition": 8
    },
    {
      "name": "mathtt",
      "text": "\\mathtt{mathtt - ABab12}",
      "value": "\\mathtt{}",
      "caretPosition": 8
    },
    {
      "name": "mathscr",
      "text": "\\mathscr{mathscr - ABab12}",
      "value": "\\mathscr{}",
      "caretPosition": 9
    },
    {
      "name": "mathfrak",
      "text": "\\mathfrak{mathfrak - ABab12}",
      "value": "\\mathfrak{}",
      "caretPosition": 10
    }
  ]
}
